README.md
setup.cfg
setup.py
filter_pandoc_run_py/__init__.py
filter_pandoc_run_py/filter_pandoc_run_py.py
filter_pandoc_run_py.egg-info/PKG-INFO
filter_pandoc_run_py.egg-info/SOURCES.txt
filter_pandoc_run_py.egg-info/dependency_links.txt
filter_pandoc_run_py.egg-info/entry_points.txt
filter_pandoc_run_py.egg-info/not-zip-safe
filter_pandoc_run_py.egg-info/requires.txt
filter_pandoc_run_py.egg-info/top_level.txt