Metadata-Version: 1.1
Name: filter-pandoc-run-py
Version: 0.2
Summary: Run python code from a markdown file and output print or images it
Home-page: https://github.com/caiofcm/filter_pandoc_run_py
Author: Caio Marcellos
Author-email: caiocuritiba@gmail.com
License: MIT
Download-URL: https://github.com/caiofcm/filter_pandoc_run_py/archive/0.1.tar.gz
Keywords: pandoc filters markdown python notes
Platform: UNKNOWN
Classifier: Development Status :: 3 - Alpha
Classifier: Topic :: Utilities
Classifier: License :: OSI Approved :: BSD License
Classifier: Programming Language :: Python :: 3.4
Classifier: Programming Language :: Python :: 3.5
Classifier: Programming Language :: Python :: 3.6
Classifier: Environment :: Console
Classifier: Intended Audience :: End Users/Desktop
Classifier: Intended Audience :: Developers
Classifier: Topic :: Software Development :: Build Tools
Classifier: Topic :: Software Development :: Documentation
Classifier: Topic :: Text Processing :: Filters
